metabo_adni/__init__.py
metabo_adni/__main__.py
metabo_adni/data/__init__.py
metabo_adni/data/load.py
metabo_adni/qc/__init__.py
metabo_adni/qc/metabolites.py
metabo_adni/qc/participants.py
metabo_adni/qc/transformations.py
metabo_adni-0.5.8.dist-info/LICENSE
metabo_adni-0.5.8.dist-info/METADATA
metabo_adni-0.5.8.dist-info/WHEEL
metabo_adni-0.5.8.dist-info/entry_points.txt
metabo_adni-0.5.8.dist-info/RECORD
