Metadata-Version: 2.1
Name: metabo_adni
Version: 0.5.8
Summary: Metabolomics data processing for the ADNI data sets.
Home-page: https://github.com/tomszar/metabo_adni
License: GNU General Public License v3.0
Keywords: metabolomics,quality control,adni,alzheimer's disease
Author: Tomas Gonzalez Zarzar
Author-email: tomasgzarzar@gmail.com
Requires-Python: >=3.12,<4.0
Classifier: License :: OSI Approved :: GNU General Public License v3 (GPLv3)
Classifier: License :: Other/Proprietary License
Classifier: Operating System :: OS Independent
Classifier: Programming Language :: Python :: 3
Classifier: Programming Language :: Python :: 3.12
Requires-Dist: openpyxl (>=3.1,<4.0)
Requires-Dist: pandas (>=2.2,<3.0)
Requires-Dist: pingouin (==0.5.4)
Project-URL: Repository, https://github.com/tomszar/metabo_adni
